AutomationJobs/__init__.py
AutomationJobs/runemail.py
AutomationJobs/Mails/__init__.py
AutomationJobs/Mails/args_email.py
AutomationJobs/Mails/fetch_file_info.py
AutomationJobs/Mails/process_email.py
AutomationJobs/Mails/sending_an_email.py
automationjobs-0.1.1.dist-info/licenses/LICENSE
automationjobs-0.1.1.dist-info/METADATA
automationjobs-0.1.1.dist-info/WHEEL
automationjobs-0.1.1.dist-info/top_level.txt
automationjobs-0.1.1.dist-info/RECORD
