Metadata-Version: 2.4
Name: AutomationJobs
Version: 0.1.1
Summary: A AutomationJobs package
Home-page: https://github.com/viswanadhGowd/AutomationJobs
Author: Viswanadh
Author-email: gowd7272@gmail.com
Classifier: Programming Language :: Python :: 3
Classifier: License :: OSI Approved :: MIT License
Classifier: Operating System :: OS Independent
Requires-Python: >=3.6
License-File: LICENSE
Requires-Dist: setuptools
Dynamic: author
Dynamic: author-email
Dynamic: classifier
Dynamic: description
Dynamic: description-content-type
Dynamic: home-page
Dynamic: license-file
Dynamic: requires-dist
Dynamic: requires-python
Dynamic: summary
